README.rst
setup.cfg
setup.py
sitemapbuilder/__init__.py
sitemapbuilder/linkvisitor.py
sitemapbuilder/sitemap_converters.py
sitemapbuilder/urlhtmlparser.py
sitemapbuilder.egg-info/PKG-INFO
sitemapbuilder.egg-info/SOURCES.txt
sitemapbuilder.egg-info/dependency_links.txt
sitemapbuilder.egg-info/requires.txt
sitemapbuilder.egg-info/top_level.txt
tools/sitemapbuilder