Metadata-Version: 1.1
Name: sitemapbuilder
Version: 0.0.7
Summary: Simple sitemap builder
Home-page: https://github.com/vietlq/sitemapbuilder
Author: Viet Le
Author-email: vietlq85@gmail.com
License: UNKNOWN
Keywords: sitemapbuilder sitemap builder http
Platform: UNKNOWN
Classifier: Development Status :: 3 - Alpha
Classifier: Environment :: Console
Classifier: Intended Audience :: Developers
Classifier: License :: OSI Approved :: Apache Software License
Classifier: Operating System :: OS Independent
Classifier: Programming Language :: Python
Classifier: Programming Language :: Python :: 3
Classifier: Programming Language :: Python :: 3.4
Classifier: Programming Language :: Python :: 3.5
Classifier: Programming Language :: Python :: 3.6
Classifier: Topic :: Software Development :: Libraries :: Python Modules
